masterthermconnect/__init__.py
masterthermconnect/__main__.py
masterthermconnect/__version__.py
masterthermconnect/api.py
masterthermconnect/const.py
masterthermconnect/controller.py
masterthermconnect/datamapread.py
masterthermconnect/datamapwrite.py
masterthermconnect/exceptions.py
masterthermconnect/special.py
masterthermconnect-2.3.2.dist-info/licenses/LICENSE
masterthermconnect-2.3.2.dist-info/METADATA
masterthermconnect-2.3.2.dist-info/WHEEL
masterthermconnect-2.3.2.dist-info/entry_points.txt
masterthermconnect-2.3.2.dist-info/top_level.txt
masterthermconnect-2.3.2.dist-info/RECORD
