Metadata-Version: 2.4
Name: masterthermconnect
Version: 2.3.2
Summary: Python 3 API wrapper for Mastertherm API
Author-email: Richard Holmes <richard@shedc.uk>
License: MIT License
Project-URL: Homepage, https://github.com/sHedC/python-masterthermconnect
Keywords: Mastertherm heatpump,api,client
Classifier: Programming Language :: Python :: 3
Classifier: License :: OSI Approved :: MIT License
Classifier: Operating System :: OS Independent
Requires-Python: <3.14,>=3.9
License-File: LICENSE
Requires-Dist: aiohttp>=3.9.1
Requires-Dist: natsort>=8.3.1
Provides-Extra: dev
Requires-Dist: black; extra == "dev"
Requires-Dist: bumpver; extra == "dev"
Requires-Dist: isort; extra == "dev"
Requires-Dist: pip-tools; extra == "dev"
Requires-Dist: pytest; extra == "dev"
Dynamic: license-file
